gradient_descent_py/__init__.py
gradient_descent_py-0.0.1.dist-info/LICENSE
gradient_descent_py-0.0.1.dist-info/METADATA
gradient_descent_py-0.0.1.dist-info/WHEEL
gradient_descent_py-0.0.1.dist-info/top_level.txt
gradient_descent_py-0.0.1.dist-info/RECORD
