Metadata-Version: 2.1
Name: gradient-descent-py
Version: 0.0.1
Summary: A gradient descent to python
Home-page: https://github.com/Cereceres/gradient-descent-py
Author: Jesus Edel Cereceres Delgado
Author-email: jesus.edelcereceres@gmail.com
License: UNKNOWN
Platform: UNKNOWN
Classifier: Programming Language :: Python :: 3
Classifier: License :: OSI Approved :: MIT License
Classifier: Operating System :: OS Independent
